pytfbot/__init__.py
pytfbot-0.1.0.dist-info/LICENSE
pytfbot-0.1.0.dist-info/WHEEL
pytfbot-0.1.0.dist-info/METADATA
pytfbot-0.1.0.dist-info/RECORD
