Metadata-Version: 2.1
Name: pytfbot
Version: 0.1.0
Summary: 
Author: tonio213
Author-email: 1956749+tonio213@users.noreply.github.com
Requires-Python: >=3.10,<4.0
Classifier: Programming Language :: Python :: 3
Classifier: Programming Language :: Python :: 3.10
Requires-Dist: SQLAlchemy (>=1.4.39,<2.0.0)
